gtalk/__init__.py
gtalk/cli.py
gtalk-1.0.8.dist-info/licenses/LICENSE
gtalk-1.0.8.dist-info/METADATA
gtalk-1.0.8.dist-info/WHEEL
gtalk-1.0.8.dist-info/entry_points.txt
gtalk-1.0.8.dist-info/top_level.txt
gtalk-1.0.8.dist-info/RECORD
