Metadata-Version: 2.4
Name: gtalk
Version: 1.0.8
Summary: Interactive terminal interface for Google AI Mode - get AI-powered answers, code examples, and explanations directly in your command line
Home-page: https://github.com/hissain/gtalk
Author: Md. Sazzad Hissain Khan
Author-email: "Md. Sazzad Hissain Khan" <hissain.khan@gmail.com>
Maintainer: Md. Sazzad Hissain Khan
Maintainer-email: hissain.khan@gmail.com
License: MIT
Project-URL: Homepage, https://github.com/hissain/gtalk
Project-URL: Documentation, https://github.com/hissain/gtalk#readme
Project-URL: Repository, https://github.com/hissain/gtalk
Project-URL: Bug Tracker, https://github.com/hissain/gtalk/issues
Project-URL: Changelog, https://github.com/hissain/gtalk/releases
Keywords: google,ai,aimode,cli,terminal,search,assistant,chatbot,artificial-intelligence,command-line,interactive,code-examples,query,open-source
Classifier: Development Status :: 5 - Production/Stable
Classifier: Intended Audience :: Developers
Classifier: Intended Audience :: Education
Classifier: Intended Audience :: Science/Research
Classifier: Topic :: Software Development :: Libraries :: Python Modules
Classifier: Topic :: Internet :: WWW/HTTP :: Dynamic Content
Classifier: Topic :: Utilities
Classifier: License :: OSI Approved :: MIT License
Classifier: Programming Language :: Python :: 3
Classifier: Programming Language :: Python :: 3.8
Classifier: Programming Language :: Python :: 3.9
Classifier: Programming Language :: Python :: 3.10
Classifier: Programming Language :: Python :: 3.11
Classifier: Programming Language :: Python :: 3.12
Classifier: Operating System :: OS Independent
Classifier: Operating System :: MacOS
Classifier: Operating System :: POSIX :: Linux
Classifier: Operating System :: Microsoft :: Windows
Classifier: Environment :: Console
Classifier: Natural Language :: English
Requires-Python: >=3.8
License-File: LICENSE
Requires-Dist: selenium>=4.15.0
Requires-Dist: beautifulsoup4>=4.12.0
Dynamic: author
Dynamic: home-page
Dynamic: license-file
Dynamic: maintainer
Dynamic: maintainer-email
Dynamic: requires-python
